[
    {
        "id": 1,
        "name": "Turael",
        "url": "https:\/\/runescape.wiki\/w\/Turael",
        "task-counts": {
            "Birds": "10-20",
            "Cave bugs": "10-20",
            "Cows": "10-25",
            "Crawling hands": "10-20",
            "Gelatinous abominations": "10-20",
            "Trolls": "10-20",
            "Wolves": "10-20"
        }
    },
    {
        "id": 2,
        "name": "Jacquelyn",
        "url": "https:\/\/runescape.wiki\/w\/Jacquelyn",
        "task-counts": {
            "Bats": "15-30",
            "Birds": "15-30",
            "Cave bugs": "15-30",
            "Cave slimes": "10-25",
            "Cows": "15-30",
            "Frogs": "15-30",
            "Ghosts": "15-25",
            "Goblins": "15-30",
            "Rats": "15-30",
            "Skeletons": "15-25",
            "Spiders": "15-25",
            "Zombies": "15-30"
        }
    },
    {
        "id": 3,
        "name": "Vannaka",
        "url": "https:\/\/runescape.wiki\/w\/Vannaka",
        "task-counts": {
            "Bats": "40-60",
            "Bears": "20-40",
            "Catablepon": "40-60",
            "Cave slimes": "40-60",
            "Cockroaches": "40-60",
            "Fleshcrawlers": "40-60",
            "Frogs": "40-60",
            "Ghosts": "40-70",
            "Grotworms": "40-60",
            "Hill giants": "40-60",
            "Hobgoblins": "40-60",
            "Ice giants": "40-60",
            "Ice warriors": "40-60",
            "Icefiends": "40-60",
            "Kalphite": "40-60",
            "Minotaurs": "40-60",
            "Mogres": "40-60",
            "Moss giants": "40-60",
            "Scorpions": "40-60",
            "Skeletons": "40-60",
            "Spiders": "40-60",
            "Wall beasts": "10-20",
            "Wolves": "40-60",
            "Zombies": "40-60"
        }
    },
    {
        "id": 4,
        "name": "The Raptor",
        "url": "https:\/\/runescape.wiki\/w\/The_Raptor",
        "task-counts": {
            "Aberrant spectres": "50-80",
            "Abyssal Demons": "140-260",
            "Acheron mammoths": "20-45",
            "Ankou": "80-120",
            "Armoured phantoms": "45-55",
            "Aviansies": "50-110",
            "Black demons": "110-160",
            "Black dragons": "70-120",
            "Camel warriors": "30-55",
            "Dagannoth": "190-250",
            "Dark beasts": "120-180",
            "Demons": "45-90",
            "Dragons": "60-90",
            "Fetid zombies": "140-170",
            "Fire giants": "110-160",
            "Ghosts": "160-180",
            "Greater demons": "140-200",
            "Green dragons": "70-120",
            "Grotworms": "140-190",
            "Hellhounds": "70-110",
            "Kalphite": "65-110",
            "Lesser demons": "120-180",
            "Living wyverns": "40-65",
            "Ripper demons": "40-65",
            "Risen ghosts": "90-120",
            "Skeletons": "95-125",
            "Undead": "130-170",
            "Zemouregal's undead": "110-150",
            "Zombies": "100-140"
        }
    },
    {
        "id": 5,
        "name": "Mazchna",
        "url": "https:\/\/runescape.wiki\/w\/Mazchna",
        "task-counts": {
            "Ankou": "60-100",
            "Banshees": "50-90",
            "Basilisks": "60-100",
            "Bloodveld": "60-100",
            "Brine rats": "60-100",
            "Cave crawlers": "50-90",
            "Cockatrice": "50-90",
            "Crocodiles": "50-90",
            "Cyclopes": "50-90",
            "Desert lizards": "50-90",
            "Dogs": "50-90",
            "Earth warriors": "35-55",
            "Ghouls": "60-100",
            "Green dragons": "35-55",
            "Grotworms": "60-100",
            "Ice giants": "50-90",
            "Ice warriors": "40-60",
            "Infernal mages": "60-100",
            "Jellies": "60-100",
            "Jungle horrors": "60-100",
            "Killerwatts": "60-100",
            "Lesser demons": "60-100",
            "Molanisks": "50-90",
            "Moss giants": "50-90",
            "Ogres": "60-100",
            "Otherworldly beings": "60-100",
            "Pyrefiends": "60-100",
            "Rockslugs": "50-90",
            "Sea snakes": "60-100",
            "Shades": "60-100",
            "Shadow warriors": "60-100",
            "Turoth": "60-100",
            "Vampyres": "50-90",
            "Werewolves": "50-90"
        }
    },
    {
        "id": 6,
        "name": "Chaeldar",
        "url": "https:\/\/runescape.wiki\/w\/Chaeldar",
        "task-counts": {
            "Aberrant spectres": "110-170",
            "Banshees": "110-170",
            "Basilisks": "110-170",
            "Bloodveld": "110-170",
            "Blue dragons": "110-170",
            "Brine rats": "110-170",
            "Bronze dragons": "30-60",
            "Cave crawlers": "110-170",
            "Cave horrors": "110-170",
            "Crawling hands": "110-170",
            "Dagannoth": "110-170",
            "Dust devils": "110-170",
            "Elves": "60-90",
            "Fever spiders": "110-170",
            "Fire giants": "110-170",
            "Fungal magi": "80-105",
            "Gargoyles": "110-170",
            "Grifolapines": "50-65",
            "Grifolaroos": "50-65",
            "Grotworms": "70-110",
            "Harpie bug swarms": "110-170",
            "Infernal mages": "110-170",
            "Jellies": "110-170",
            "Jungle horrors": "110-170",
            "Jungle strykewyrms": "80-110",
            "Kalphite": "110-170",
            "Kurask": "110-170",
            "Lesser demons": "110-170",
            "Mutated zygomites": "30-60",
            "Shadow warriors": "110-170",
            "Trolls": "110-170",
            "Turoth": "110-170",
            "Vyrewatch": "80-110",
            "Warped tortoises": "110-170"
        }
    },
    {
        "id": 7,
        "name": "Sumona",
        "url": "https:\/\/runescape.wiki\/w\/Sumona",
        "task-counts": {
            "Aberrant spectres": "120-185",
            "Abyssal Demons": "120-185",
            "Aquanites": "120-185",
            "Aviansies": "50-100",
            "Banshees": "120-185",
            "Basilisks": "120-185",
            "Black demons": "120-185",
            "Bloodveld": "120-185",
            "Blue dragons": "120-185",
            "Cave crawlers": "120-185",
            "Cave horrors": "120-185",
            "Corrupted creatures": "175-300",
            "Cres's creations": "65-80",
            "Crocodiles": "150-250",
            "Dagannoth": "120-185",
            "Desert lizards": "150-250",
            "Desert strykewyrms": "90-110",
            "Dust devils": "120-185",
            "Elves": "60-90",
            "Fire giants": "120-185",
            "Fungal magi": "90-110",
            "Gargoyles": "120-195",
            "Greater demons": "120-185",
            "Grifolapines": "55-75",
            "Grifolaroos": "55-75",
            "Grotworms": "70-120",
            "Hellhounds": "120-185",
            "Iron dragons": "30-60",
            "Jungle strykewyrms": "90-120",
            "Kalphite": "120-185",
            "Kurask": "120-185",
            "Mutated jadinkos": "80-130",
            "Nechryael": "120-185",
            "Red dragons": "30-60",
            "Scabarites": "30-60",
            "Scorpions": "150-250",
            "Soul devourers": "175-300",
            "Spiritual mages": "120-185",
            "Spiritual warriors": "120-185",
            "Terror dogs": "30-60",
            "Trolls": "120-185",
            "Turoth": "120-185",
            "Vyrewatch": "90-120",
            "Warped tortoises": "120-185"
        }
    },
    {
        "id": 8,
        "name": "Duradel",
        "url": "https:\/\/runescape.wiki\/w\/Duradel",
        "task-counts": {
            "Aberrant spectres": "130-200",
            "Abyssal Demons": "130-200",
            "Airut": "125-150",
            "Aquanites": "130-200",
            "Ascension members": "100-125",
            "Aviansies": "100-125",
            "Black demons": "130-200",
            "Black dragons": "40-80",
            "Bloodveld": "130-200",
            "Celestial dragons": "125-150",
            "Cres's creations": "65-80",
            "Dagannoth": "130-200",
            "Dark beasts": "130-200",
            "Desert strykewyrms": "90-140",
            "Dust devils": "130-200",
            "Edimmu": "130-200",
            "Fire giants": "130-200",
            "Fungal magi": "100-200",
            "Ganodermic creatures": "55-70",
            "Gargoyles": "130-200",
            "Goraks": "40-80",
            "Greater demons": "130-200",
            "Grifolapines": "60-85",
            "Grifolaroos": "60-85",
            "Grotworms": "80-120",
            "Hellhounds": "130-200",
            "Ice strykewyrms": "100-200",
            "Iron dragons": "40-80",
            "Jungle strykewyrms": "90-120",
            "Kalphite": "130-200",
            "Mithril dragons": "4-8",
            "Mutated jadinkos": "120-200",
            "Nechryael": "130-200",
            "Scabarites": "40-80",
            "Skeletal wyverns": "40-80",
            "Spiritual mages": "130-200",
            "Steel dragons": "40-80",
            "Suqahs": "40-80",
            "Vyrewatch": "90-120",
            "Warped terrorbirds": "130-200",
            "Waterfiends": "130-200"
        }
    },
    {
        "id": 9,
        "name": "Kuradal",
        "url": "https:\/\/runescape.wiki\/w\/Kuradal",
        "task-counts": {
            "Aberrant spectres": "150-250",
            "Abyssal Demons": "150-250",
            "Acheron mammoths": "20-45",
            "Adamant dragons": "40-50",
            "Airut": "125-150",
            "Aquanites": "160-200",
            "Ascension members": "100-125",
            "Aviansies": "125-150",
            "Black demons": "190-250",
            "Black dragons": "40-90",
            "Bloodveld": "180-250",
            "Blue dragons": "120-200",
            "Camel warriors": "25-45",
            "Celestial dragons": "125-150",
            "Chaos giants": "60-100",
            "Corrupted creatures": "150-250",
            "Cres's creations": "65-80",
            "Dagannoth": "170-240",
            "Dark beasts": "150-250",
            "Desert strykewyrms": "90-160",
            "Dust devils": "150-250",
            "Edimmu": "150-250",
            "Elves": "120-150",
            "Fire giants": "170-250",
            "Ganodermic creatures": "70-90",
            "Gargoyles": "150-250",
            "Gemstone dragons": "60-100",
            "Glacors": "50-70",
            "Greater demons": "150-250",
            "Grifolapines": "65-80",
            "Grifolaroos": "65-80",
            "Grotworms": "80-150",
            "Hellhounds": "130-220",
            "Ice strykewyrms": "100-200",
            "Iron dragons": "60-110",
            "Jungle strykewyrms": "90-130",
            "Kal'gerion demons": "50-100",
            "Kalphite": "170-250",
            "Lava strykewyrms": "50-100",
            "Living rock creatures": "120-170",
            "Living wyverns": "30-55",
            "Mithril dragons": "30-35",
            "Muspah": "125-150",
            "Mutated jadinkos": "160-220"
        }
    },
    {
        "id": 10,
        "name": "Morvran",
        "url": "https:\/\/runescape.wiki\/w\/Morvran",
        "task-counts": {
            "Abyssal Demons": "180-300",
            "Acheron mammoths": "30-55",
            "Adamant dragons": "40-60",
            "Airut": "150-180",
            "Aquanites": "195-240",
            "Ascension members": "120-150",
            "Aviansies": "150-180",
            "Black demons": "230-300",
            "Black dragons": "50-110",
            "Camel warriors": "35-55",
            "Celestial dragons": "150-180",
            "Chaos giants": "80-120",
            "Corrupted creatures": "150-250",
            "Creatures of the Lost Grove": "100-120",
            "Cres's creations": "80-100",
            "Crystal shapeshifters": "110-150",
            "Dagannoth": "205-290",
            "Dark beasts": "180-300",
            "Desert strykewyrms": "110-190",
            "Edimmu": "170-265",
            "Elves": "150-180",
            "Ganodermic creatures": "85-110",
            "Gargoyles": "180-300",
            "Gemstone dragons": "80-130",
            "Glacors": "60-85",
            "Greater demons": "180-300",
            "Grotworms": "100-180",
            "Ice strykewyrms": "120-240",
            "Iron dragons": "75-130",
            "Kal'gerion demons": "60-120",
            "Kalphite": "205-300",
            "Lava strykewyrms": "60-120",
            "Living wyverns": "40-65",
            "Mithril dragons": "30-50",
            "Muspah": "150-180",
            "Mutated jadinkos": "195-265",
            "Nechryael": "170-265",
            "Nightmare creatures": "110-160",
            "Nihil": "50-110",
            "Nodon dragonkin": "90-130",
            "Ripper demons": "60-85",
            "Rune dragons": "50-75",
            "Shadow creatures": "100-150"
        }
    },
    {
        "id": 11,
        "name": "Laniakea",
        "url": "https:\/\/runescape.wiki\/w\/Laniakea",
        "task-counts": {
            "Abyssal Demons": "180-300",
            "Acheron mammoths": "30-55",
            "Adamant dragons": "40-60",
            "Airut": "150-180",
            "Aquanites": "195-240",
            "Armoured phantoms": "55-65",
            "Ascension members": "120-150",
            "Aviansies": "150-180",
            "Black demons": "230-300",
            "Black dragons": "50-110",
            "Camel warriors": "35-55",
            "Celestial dragons": "150-180",
            "Chaos giants": "80-120",
            "Corrupted creatures": "150-250",
            "Creatures of Daemonheim": "101-150",
            "Creatures of the Lost Grove": "100-120",
            "Cres's creations": "80-100",
            "Crystal shapeshifters": "110-150",
            "Dagannoth": "205-290",
            "Dark beasts": "180-300",
            "Demons": "101-150",
            "Dinosaurs": "70-110",
            "Dragons": "101-150",
            "Edimmu": "170-265",
            "Elves": "150-180",
            "Ganodermic creatures": "85-110",
            "Gargoyles": "180-300",
            "Gemstone dragons": "80-130",
            "Glacors": "60-85",
            "Greater demons": "180-300",
            "Ice strykewyrms": "120-240",
            "Iron dragons": "75-130",
            "Kal'gerion demons": "60-120",
            "Kalphite": "205-300",
            "Lava strykewyrms": "60-120",
            "Living wyverns": "40-65",
            "Mithril dragons": "30-50",
            "Muspah": "150-180",
            "Mutated jadinkos": "195-265",
            "Nightmare creatures": "110-162",
            "Nihil": "50-110",
            "Nodon dragonkin": "110-150",
            "Ripper demons": "60-85"
        }
    },
    {
        "id": 12,
        "name": "Mandrith",
        "url": "https:\/\/runescape.wiki\/w\/Mandrith",
        "task-counts": {
            "Abyssal beasts": "140-200",
            "Abyssal Demons": "180-300",
            "Abyssal lords": "100-150",
            "Abyssal savages": "180-250",
            "Acheron mammoths": "40-60",
            "Black demons": "200-280",
            "Dark beasts": "180-300",
            "Gargoyles": "180-300",
            "Glacors": "70-100",
            "Greater demon berserkers and ash lords": "50-80",
            "Hydrix dragons": "90-140",
            "Ice strykewyrms": "100-150",
            "Kal'gerion demons": "60-120",
            "Lava strykewyrms": "60-120",
            "Living wyverns": "50-75",
            "Onyx dragons": "100-150",
            "Revenants": "50-80",
            "Ripper demons": "70-95",
            "Soulgazers": "140-190"
        }
    }
]